pysensing/__init__.py
pysensing/_version.py
pysensing-0.0.2.dist-info/LICENSE
pysensing-0.0.2.dist-info/METADATA
pysensing-0.0.2.dist-info/WHEEL
pysensing-0.0.2.dist-info/top_level.txt
pysensing-0.0.2.dist-info/zip-safe
pysensing-0.0.2.dist-info/RECORD
